appcontext/__init__.py
appcontext/exceptions.py
appcontext/global_settings.py
appcontext/utils.py
appcontext-0.1.0.dist-info/LICENSE
appcontext-0.1.0.dist-info/WHEEL
appcontext-0.1.0.dist-info/METADATA
appcontext-0.1.0.dist-info/RECORD
