Metadata-Version: 2.1
Name: appcontext
Version: 0.1.0
Summary: Simple application configuration
Home-page: https://www.github.com.com/a2d24/appcontext
License: MIT
Author: Imtiaz Mangerah
Author-email: Imtiaz_Mangerah@a2d24.com
Requires-Python: >=3.6,<4.0
Classifier: License :: OSI Approved :: MIT License
Classifier: Programming Language :: Python :: 3
Classifier: Programming Language :: Python :: 3.6
Classifier: Programming Language :: Python :: 3.7
Classifier: Programming Language :: Python :: 3.8
Classifier: Programming Language :: Python :: 3.9
Project-URL: Documentation, https://www.github.com.com/a2d24/appcontext
Project-URL: Repository, https://www.github.com.com/a2d24/appcontext
